sirius
sirius_data
sirius_tests
