Metadata-Version: 2.1
Name: sirius
Version: 0.0.21
Summary: Simulation of Radio Interferometry from Unique Sources
Home-page: https://github.com/casangi/sirius
Author: National Radio Astronomy Observatory
Author-email: casa-feedback@nrao.edu
License: Apache-2.0
Platform: UNKNOWN
Provides-Extra: dev
